zhong_hong_hvac/__init__.py
zhong_hong_hvac/helper.py
zhong_hong_hvac/hub.py
zhong_hong_hvac/hvac.py
zhong_hong_hvac/protocol.py
zhong_hong_hvac/version.py
zhong_hong_hvac-1.0.13.dist-info/LICENSE
zhong_hong_hvac-1.0.13.dist-info/METADATA
zhong_hong_hvac-1.0.13.dist-info/WHEEL
zhong_hong_hvac-1.0.13.dist-info/RECORD
