Metadata-Version: 2.1
Name: zhong-hong-hvac
Version: 1.0.13
Summary: Python library for interfacing with ZhongHong HVAC controller
License: Apache
Author: ruohan.chen
Author-email: crhan123@gmail.com
Requires-Python: >=3.9,<4.0
Classifier: Development Status :: 4 - Beta
Classifier: Intended Audience :: Developers
Classifier: License :: OSI Approved :: Apache Software License
Classifier: License :: Other/Proprietary License
Classifier: Programming Language :: Python :: 3
Classifier: Programming Language :: Python :: 3.9
Classifier: Programming Language :: Python :: 3.10
Classifier: Programming Language :: Python :: 3.11
Classifier: Programming Language :: Python :: 3.12
Classifier: Programming Language :: Python :: 3 :: Only
Classifier: Programming Language :: Python :: 3.5
Classifier: Programming Language :: Python :: 3.6
Classifier: Programming Language :: Python :: 3.7
Classifier: Programming Language :: Python :: 3.8
Requires-Dist: attrs (>=23.1.0)
Project-URL: homepage, https://pypi.org/project/zhong-hong-hvac
Project-URL: repository, https://github.com/crhan/ZhongHongHVAC
